{
  "version": "0.13.0",
  "description": "BSON encoding/decoding, used in MongoDB drivers",
  "name": "BSON",

  "perl": "6.d",
  "license": "Artistic-2.0",
  "tags": [ "bson", "binary json", "serialize"],

  "authors": [
    "Marcel Timmerman",
    "Paweł Pabian"
  ],

  "provides": {
    "BSON":                      "lib/BSON.pm6",
    "BSON::Binary":              "lib/BSON/Binary.pm6",
    "BSON::Decimal128::Actions": "lib/BSON/Decimal128/Actions.pm6",
    "BSON::Decimal128::Grammar": "lib/BSON/Decimal128/Grammar.pm6",
    "BSON::Decimal128":          "lib/BSON/Decimal128.pm6",
    "BSON::Decode":              "lib/BSON/Decode.pm6",
    "BSON::Document":            "lib/BSON/Document.pm6",
    "BSON::Encode":              "lib/BSON/Encode.pm6",
    "BSON::Javascript":          "lib/BSON/Javascript.pm6",
    "BSON::ObjectId":            "lib/BSON/ObjectId.pm6",
    "BSON::Ordered":             "lib/BSON/Ordered.pm6",
    "BSON::Regex":               "lib/BSON/Regex.pm6"
  },

  "history": [
    "Paweł Pabian worked on it from 2011 until January 2015",
    "Marcel Timmerman took over in Januari 2015 and is working on it until the present day"
  ],

  "depends": [
    "OpenSSL", "UUID", "Method::Also"
  ],

  "build-depends": [ ],
  "test-depends": [ ],

  "source-url": "git://github.com/MARTIMM/BSON.git"
}
